MANIFEST.in
README.rst
setup.py
aliyun_python_sdk_acms_open.egg-info/PKG-INFO
aliyun_python_sdk_acms_open.egg-info/SOURCES.txt
aliyun_python_sdk_acms_open.egg-info/dependency_links.txt
aliyun_python_sdk_acms_open.egg-info/requires.txt
aliyun_python_sdk_acms_open.egg-info/top_level.txt
aliyunsdkacms_open/__init__.py
aliyunsdkacms_open/endpoint.py
aliyunsdkacms_open/request/__init__.py
aliyunsdkacms_open/request/v20200206/CreateConfigurationRequest.py
aliyunsdkacms_open/request/v20200206/CreateNamespaceRequest.py
aliyunsdkacms_open/request/v20200206/DeleteConfigurationRequest.py
aliyunsdkacms_open/request/v20200206/DeleteNamespaceRequest.py
aliyunsdkacms_open/request/v20200206/DeployConfigurationRequest.py
aliyunsdkacms_open/request/v20200206/DescribeConfigurationRequest.py
aliyunsdkacms_open/request/v20200206/DescribeNamespaceRequest.py
aliyunsdkacms_open/request/v20200206/UpdateNamespaceRequest.py
aliyunsdkacms_open/request/v20200206/__init__.py